MANIFEST.in
README.txt
setup.py
docs/HISTORY.txt
src/silva/__init__.py
src/silva.core.messages.egg-info/PKG-INFO
src/silva.core.messages.egg-info/SOURCES.txt
src/silva.core.messages.egg-info/dependency_links.txt
src/silva.core.messages.egg-info/namespace_packages.txt
src/silva.core.messages.egg-info/not-zip-safe
src/silva.core.messages.egg-info/requires.txt
src/silva.core.messages.egg-info/top_level.txt
src/silva/core/__init__.py
src/silva/core/messages/__init__.py
src/silva/core/messages/configure.zcml
src/silva/core/messages/ftesting.zcml
src/silva/core/messages/interfaces.py
src/silva/core/messages/service.py
src/silva/core/messages/tests/__init__.py
src/silva/core/messages/tests/test_service.py