Metadata-Version: 1.1
Name: silva.core.messages
Version: 2.3
Summary: User feedback mechanism for Silva CMS
Home-page: https://github.com/silvacms/silva.core.messages
Author: Infrae
Author-email: info@infrae.com
License: BSD
Keywords: silva core messages
Platform: UNKNOWN
Classifier: Framework :: Zope2
Classifier: Programming Language :: Python
Classifier: Topic :: Software Development :: Libraries :: Python Modules
Classifier: License :: OSI Approved :: BSD License
